reasoning_library/__init__.py
reasoning_library/abductive.py
reasoning_library/chain_of_thought.py
reasoning_library/concurrent_security_logging.py
reasoning_library/constants.py
reasoning_library/core.py
reasoning_library/deductive.py
reasoning_library/engine.py
reasoning_library/exceptions.py
reasoning_library/inductive.py
reasoning_library/null_handling.py
reasoning_library/persistent_rate_limiting.py
reasoning_library/sanitization.py
reasoning_library/security_event_dispatcher.py
reasoning_library/security_events.py
reasoning_library/security_factory.py
reasoning_library/security_logging.py
reasoning_library/thread_safety.py
reasoning_library/validation.py
reasoning_library-0.2.2.dist-info/METADATA
reasoning_library-0.2.2.dist-info/WHEEL
reasoning_library-0.2.2.dist-info/licenses/LICENSE
reasoning_library-0.2.2.dist-info/RECORD
