Metadata-Version: 2.4
Name: reasoning-library
Version: 0.2.2
Summary: A Python library for formal reasoning methods with LLM integration
Project-URL: Homepage, https://github.com/democratize-technology/reasoning_library
Project-URL: Repository, https://github.com/democratize-technology/reasoning_library
Project-URL: Documentation, https://github.com/democratize-technology/reasoning_library#readme
Project-URL: Issues, https://github.com/democratize-technology/reasoning_library/issues
Author: reasoning-library contributors
License: MIT
License-File: LICENSE
Keywords: ai,functional-programming,llm,logic,reasoning
Classifier: Development Status :: 4 - Beta
Classifier: Intended Audience :: Developers
Classifier: Intended Audience :: Science/Research
Classifier: License :: OSI Approved :: MIT License
Classifier: Programming Language :: Python :: 3
Classifier: Programming Language :: Python :: 3.10
Classifier: Programming Language :: Python :: 3.11
Classifier: Programming Language :: Python :: 3.12
Classifier: Topic :: Scientific/Engineering :: Artificial Intelligence
Classifier: Topic :: Software Development :: Libraries :: Python Modules
Requires-Python: >=3.10
Requires-Dist: numpy>=1.24.0
Provides-Extra: dev
Requires-Dist: black>=23.0.0; extra == 'dev'
Requires-Dist: isort>=5.12.0; extra == 'dev'
Requires-Dist: mypy>=1.0.0; extra == 'dev'
Requires-Dist: pre-commit>=3.0.0; extra == 'dev'
Requires-Dist: pytest-cov>=4.0.0; extra == 'dev'
Requires-Dist: pytest>=7.0.0; extra == 'dev'
Provides-Extra: test
Requires-Dist: pytest-cov>=4.0.0; extra == 'test'
Requires-Dist: pytest>=7.0.0; extra == 'test'
